{
    "openapi": "3.0.0",
    "info": {
        "title": "Cervezas de Importación e-commerce",
        "description": "Descripcion",
        "version": "1.0"
    },
    "servers": [
        {
            "url": "http://localhost:8000"
        }
    ],
    "paths": {
        "/api/v1/cervezas": {
            "get": {
                "tags": [
                    "Cervezas"
                ],
                "summary": "Obtener la lista de cervezas",
                "description": "Devuelve la lista de cervezas",
                "operationId": "getCervezasList",
                "parameters": [
                    {
                        "name": "per_page",
                        "in": "query",
                        "description": "Number of items per page",
                        "required": false,
                        "schema": {
                            "type": "integer"
                        }
                    },
                    {
                        "name": "page",
                        "in": "query",
                        "description": "Page number",
                        "required": false,
                        "schema": {
                            "type": "integer"
                        }
                    },
                    {
                        "name": "color_id",
                        "in": "query",
                        "description": "Filter by color ID",
                        "required": false,
                        "schema": {
                            "type": "integer"
                        }
                    },
                    {
                        "name": "pais_id",
                        "in": "query",
                        "description": "Filter by pais ID",
                        "required": false,
                        "schema": {
                            "type": "integer"
                        }
                    },
                    {
                        "name": "tipo_id",
                        "in": "query",
                        "description": "Filter by tipo ID",
                        "required": false,
                        "schema": {
                            "type": "integer"
                        }
                    },
                    {
                        "name": "novedad",
                        "in": "query",
                        "description": "Filter by novedad",
                        "required": false,
                        "schema": {
                            "type": "boolean"
                        }
                    },
                    {
                        "name": "oferta",
                        "in": "query",
                        "description": "Filter by oferta",
                        "required": false,
                        "schema": {
                            "type": "boolean"
                        }
                    },
                    {
                        "name": "marca",
                        "in": "query",
                        "description": "Filter by marca",
                        "required": false,
                        "schema": {
                            "type": "string"
                        }
                    },
                    {
                        "name": "precio_desde",
                        "in": "query",
                        "description": "Filter by minimum price",
                        "required": false,
                        "schema": {
                            "type": "numeric"
                        }
                    },
                    {
                        "name": "precio_hasta",
                        "in": "query",
                        "description": "Filter by maximum price",
                        "required": false,
                        "schema": {
                            "type": "numeric"
                        }
                    }
                ],
                "responses": {
                    "200": {
                        "description": "Successful operation",
                        "content": {
                            "application/json": {
                                "schema": {
                                    "type": "array",
                                    "items": {
                                        "$ref": "#/components/schemas/Cerveza"
                                    }
                                }
                            }
                        }
                    },
                    "400": {
                        "description": "Bad request"
                    }
                }
            },
            "post": {
                "tags": [
                    "Cervezas"
                ],
                "summary": "Create a new cerveza",
                "description": "Creates a new cerveza and stores it in the database",
                "operationId": "storeCerveza",
                "requestBody": {
                    "required": true,
                    "content": {
                        "application/json": {
                            "schema": {
                                "properties": {
                                    "nombre": {
                                        "type": "string"
                                    },
                                    "descripcion": {
                                        "type": "string"
                                    },
                                    "color_id": {
                                        "type": "integer"
                                    },
                                    "graduacion_id": {
                                        "type": "integer"
                                    },
                                    "tipo_id": {
                                        "type": "integer"
                                    },
                                    "pais_id": {
                                        "type": "integer"
                                    },
                                    "novedad": {
                                        "type": "boolean"
                                    },
                                    "oferta": {
                                        "type": "boolean"
                                    },
                                    "precio": {
                                        "type": "number"
                                    },
                                    "foto": {
                                        "type": "string",
                                        "format": "binary"
                                    },
                                    "marca": {
                                        "type": "string"
                                    }
                                },
                                "type": "object"
                            }
                        }
                    }
                },
                "responses": {
                    "201": {
                        "description": "Cerveza created successfully",
                        "content": {
                            "application/json": {
                                "schema": {
                                    "properties": {
                                        "id": {
                                            "type": "integer"
                                        },
                                        "nombre": {
                                            "type": "string"
                                        },
                                        "descripcion": {
                                            "type": "string"
                                        },
                                        "color_id": {
                                            "type": "integer"
                                        },
                                        "graduacion_id": {
                                            "type": "integer"
                                        },
                                        "tipo_id": {
                                            "type": "integer"
                                        },
                                        "pais_id": {
                                            "type": "integer"
                                        },
                                        "novedad": {
                                            "type": "boolean"
                                        },
                                        "oferta": {
                                            "type": "boolean"
                                        },
                                        "precio": {
                                            "type": "number"
                                        },
                                        "foto": {
                                            "type": "string"
                                        },
                                        "marca": {
                                            "type": "string"
                                        }
                                    },
                                    "type": "object"
                                }
                            }
                        }
                    },
                    "400": {
                        "description": "Bad request",
                        "content": {
                            "application/json": {
                                "schema": {
                                    "properties": {
                                        "message": {
                                            "type": "string"
                                        }
                                    },
                                    "type": "object"
                                }
                            }
                        }
                    },
                    "401": {
                        "description": "Unauthorized",
                        "content": {
                            "application/json": {
                                "schema": {
                                    "properties": {
                                        "message": {
                                            "type": "string"
                                        }
                                    },
                                    "type": "object"
                                }
                            }
                        }
                    },
                    "500": {
                        "description": "Internal Server Error",
                        "content": {
                            "application/json": {
                                "schema": {
                                    "properties": {
                                        "message": {
                                            "type": "string"
                                        }
                                    },
                                    "type": "object"
                                }
                            }
                        }
                    }
                },
                "security": [
                    {
                        "bearerAuth": []
                    }
                ]
            }
        },
        "/api/v1/cervezas/{id}": {
            "get": {
                "tags": [
                    "Cervezas"
                ],
                "summary": "Get cerveza details by ID",
                "description": "Returns details of a cerveza based on its ID",
                "operationId": "getCervezaById",
                "parameters": [
                    {
                        "name": "id",
                        "in": "path",
                        "description": "ID of the cerveza",
                        "required": true,
                        "schema": {
                            "type": "string"
                        }
                    }
                ],
                "responses": {
                    "200": {
                        "description": "Successful operation",
                        "content": {
                            "application/json": {
                                "schema": {
                                    "properties": {
                                        "id": {
                                            "type": "integer"
                                        },
                                        "nombre": {
                                            "type": "string"
                                        },
                                        "descripcion": {
                                            "type": "string"
                                        },
                                        "color_id": {
                                            "type": "integer"
                                        },
                                        "graduacion_id": {
                                            "type": "integer"
                                        },
                                        "tipo_id": {
                                            "type": "integer"
                                        },
                                        "pais_id": {
                                            "type": "integer"
                                        },
                                        "novedad": {
                                            "type": "boolean"
                                        },
                                        "oferta": {
                                            "type": "boolean"
                                        },
                                        "precio": {
                                            "type": "number"
                                        },
                                        "foto": {
                                            "type": "string"
                                        },
                                        "marca": {
                                            "type": "string"
                                        }
                                    },
                                    "type": "object"
                                }
                            }
                        }
                    },
                    "404": {
                        "description": "Cerveza not found",
                        "content": {
                            "application/json": {
                                "schema": {
                                    "properties": {
                                        "message": {
                                            "type": "string"
                                        }
                                    },
                                    "type": "object"
                                }
                            }
                        }
                    },
                    "401": {
                        "description": "Unauthorized",
                        "content": {
                            "application/json": {
                                "schema": {
                                    "properties": {
                                        "message": {
                                            "type": "string"
                                        }
                                    },
                                    "type": "object"
                                }
                            }
                        }
                    },
                    "500": {
                        "description": "Internal Server Error",
                        "content": {
                            "application/json": {
                                "schema": {
                                    "properties": {
                                        "message": {
                                            "type": "string"
                                        }
                                    },
                                    "type": "object"
                                }
                            }
                        }
                    }
                }
            },
            "put": {
                "tags": [
                    "Cervezas"
                ],
                "summary": "Update cerveza details by ID",
                "description": "Updates details of a cerveza based on its ID",
                "operationId": "updateCerveza",
                "parameters": [
                    {
                        "name": "id",
                        "in": "path",
                        "description": "ID of the cerveza",
                        "required": true,
                        "schema": {
                            "type": "string"
                        }
                    }
                ],
                "requestBody": {
                    "description": "Cerveza details to be updated",
                    "required": true,
                    "content": {
                        "application/json": {
                            "schema": {
                                "properties": {
                                    "nombre": {
                                        "type": "string"
                                    },
                                    "descripcion": {
                                        "type": "string"
                                    },
                                    "color_id": {
                                        "type": "integer"
                                    },
                                    "graduacion_id": {
                                        "type": "integer"
                                    },
                                    "tipo_id": {
                                        "type": "integer"
                                    },
                                    "pais_id": {
                                        "type": "integer"
                                    },
                                    "novedad": {
                                        "type": "boolean"
                                    },
                                    "oferta": {
                                        "type": "boolean"
                                    },
                                    "precio": {
                                        "type": "number"
                                    },
                                    "foto": {
                                        "type": "string"
                                    },
                                    "marca": {
                                        "type": "string"
                                    }
                                },
                                "type": "object"
                            }
                        }
                    }
                },
                "responses": {
                    "200": {
                        "description": "Successful operation",
                        "content": {
                            "application/json": {
                                "schema": {
                                    "properties": {
                                        "id": {
                                            "type": "integer"
                                        },
                                        "nombre": {
                                            "type": "string"
                                        },
                                        "descripcion": {
                                            "type": "string"
                                        },
                                        "color_id": {
                                            "type": "integer"
                                        },
                                        "graduacion_id": {
                                            "type": "integer"
                                        },
                                        "tipo_id": {
                                            "type": "integer"
                                        },
                                        "pais_id": {
                                            "type": "integer"
                                        },
                                        "novedad": {
                                            "type": "boolean"
                                        },
                                        "oferta": {
                                            "type": "boolean"
                                        },
                                        "precio": {
                                            "type": "number"
                                        },
                                        "foto": {
                                            "type": "string"
                                        },
                                        "marca": {
                                            "type": "string"
                                        }
                                    },
                                    "type": "object"
                                }
                            }
                        }
                    },
                    "400": {
                        "description": "Bad request",
                        "content": {
                            "application/json": {
                                "schema": {
                                    "properties": {
                                        "message": {
                                            "type": "string"
                                        }
                                    },
                                    "type": "object"
                                }
                            }
                        }
                    },
                    "401": {
                        "description": "Unauthorized",
                        "content": {
                            "application/json": {
                                "schema": {
                                    "properties": {
                                        "message": {
                                            "type": "string"
                                        }
                                    },
                                    "type": "object"
                                }
                            }
                        }
                    },
                    "404": {
                        "description": "Cerveza not found",
                        "content": {
                            "application/json": {
                                "schema": {
                                    "properties": {
                                        "message": {
                                            "type": "string"
                                        }
                                    },
                                    "type": "object"
                                }
                            }
                        }
                    },
                    "500": {
                        "description": "Internal Server Error",
                        "content": {
                            "application/json": {
                                "schema": {
                                    "properties": {
                                        "message": {
                                            "type": "string"
                                        }
                                    },
                                    "type": "object"
                                }
                            }
                        }
                    }
                },
                "security": [
                    {
                        "bearerAuth": []
                    }
                ]
            },
            "delete": {
                "tags": [
                    "Cervezas"
                ],
                "summary": "Delete a cerveza by ID",
                "description": "Deletes a cerveza based on its ID",
                "operationId": "deleteCerveza",
                "parameters": [
                    {
                        "name": "id",
                        "in": "path",
                        "description": "ID of the cerveza",
                        "required": true,
                        "schema": {
                            "type": "string"
                        }
                    }
                ],
                "responses": {
                    "200": {
                        "description": "Successful operation",
                        "content": {
                            "application/json": {
                                "schema": {
                                    "properties": {
                                        "message": {
                                            "type": "string"
                                        }
                                    },
                                    "type": "object"
                                }
                            }
                        }
                    },
                    "404": {
                        "description": "Cerveza not found",
                        "content": {
                            "application/json": {
                                "schema": {
                                    "properties": {
                                        "message": {
                                            "type": "string"
                                        }
                                    },
                                    "type": "object"
                                }
                            }
                        }
                    },
                    "500": {
                        "description": "Internal Server Error",
                        "content": {
                            "application/json": {
                                "schema": {
                                    "properties": {
                                        "message": {
                                            "type": "string"
                                        }
                                    },
                                    "type": "object"
                                }
                            }
                        }
                    }
                },
                "security": [
                    {
                        "bearerAuth": []
                    }
                ]
            },
            "patch": {
                "tags": [
                    "Cervezas"
                ],
                "summary": "Patch cerveza details by ID",
                "description": "Partially updates details of a cerveza based on its ID",
                "operationId": "patchCerveza",
                "parameters": [
                    {
                        "name": "id",
                        "in": "path",
                        "description": "ID of the cerveza",
                        "required": true,
                        "schema": {
                            "type": "string"
                        }
                    }
                ],
                "requestBody": {
                    "description": "Cerveza details to be partially updated",
                    "required": true,
                    "content": {
                        "application/json": {
                            "schema": {
                                "properties": {
                                    "nombre": {
                                        "type": "string"
                                    },
                                    "descripcion": {
                                        "type": "string"
                                    },
                                    "color_id": {
                                        "type": "integer"
                                    },
                                    "graduacion_id": {
                                        "type": "integer"
                                    },
                                    "tipo_id": {
                                        "type": "integer"
                                    },
                                    "pais_id": {
                                        "type": "integer"
                                    },
                                    "novedad": {
                                        "type": "boolean"
                                    },
                                    "oferta": {
                                        "type": "boolean"
                                    },
                                    "precio": {
                                        "type": "number"
                                    },
                                    "foto": {
                                        "type": "string"
                                    },
                                    "marca": {
                                        "type": "string"
                                    }
                                },
                                "type": "object"
                            }
                        }
                    }
                },
                "responses": {
                    "200": {
                        "description": "Successful operation",
                        "content": {
                            "application/json": {
                                "schema": {
                                    "properties": {
                                        "id": {
                                            "type": "integer"
                                        },
                                        "nombre": {
                                            "type": "string"
                                        },
                                        "descripcion": {
                                            "type": "string"
                                        },
                                        "color_id": {
                                            "type": "integer"
                                        },
                                        "graduacion_id": {
                                            "type": "integer"
                                        },
                                        "tipo_id": {
                                            "type": "integer"
                                        },
                                        "pais_id": {
                                            "type": "integer"
                                        },
                                        "novedad": {
                                            "type": "boolean"
                                        },
                                        "oferta": {
                                            "type": "boolean"
                                        },
                                        "precio": {
                                            "type": "number"
                                        },
                                        "foto": {
                                            "type": "string"
                                        },
                                        "marca": {
                                            "type": "string"
                                        }
                                    },
                                    "type": "object"
                                }
                            }
                        }
                    },
                    "400": {
                        "description": "Bad request",
                        "content": {
                            "application/json": {
                                "schema": {
                                    "properties": {
                                        "message": {
                                            "type": "string"
                                        }
                                    },
                                    "type": "object"
                                }
                            }
                        }
                    },
                    "401": {
                        "description": "Unauthorized",
                        "content": {
                            "application/json": {
                                "schema": {
                                    "properties": {
                                        "message": {
                                            "type": "string"
                                        }
                                    },
                                    "type": "object"
                                }
                            }
                        }
                    },
                    "404": {
                        "description": "Cerveza not found",
                        "content": {
                            "application/json": {
                                "schema": {
                                    "properties": {
                                        "message": {
                                            "type": "string"
                                        }
                                    },
                                    "type": "object"
                                }
                            }
                        }
                    },
                    "500": {
                        "description": "Internal Server Error",
                        "content": {
                            "application/json": {
                                "schema": {
                                    "properties": {
                                        "message": {
                                            "type": "string"
                                        }
                                    },
                                    "type": "object"
                                }
                            }
                        }
                    }
                },
                "security": [
                    {
                        "bearerAuth": []
                    }
                ]
            }
        },
        "/api/v1/colores": {
            "get": {
                "tags": [
                    "Colores"
                ],
                "summary": "Obtener todos los colores",
                "description": "Recupera todos los colores de la base de datos y los devuelve como una respuesta JSON",
                "operationId": "getColores",
                "responses": {
                    "200": {
                        "description": "Lista de colores",
                        "content": {
                            "application/json": {
                                "schema": {
                                    "properties": {
                                        "colores": {
                                            "type": "array",
                                            "items": {
                                                "properties": {
                                                    "id": {
                                                        "type": "integer",
                                                        "example": 1
                                                    },
                                                    "nombre": {
                                                        "type": "string",
                                                        "example": "Rojo"
                                                    },
                                                    "codigo": {
                                                        "type": "string",
                                                        "example": "#FF0000"
                                                    }
                                                },
                                                "type": "object"
                                            }
                                        }
                                    },
                                    "type": "object"
                                }
                            }
                        }
                    }
                }
            },
            "post": {
                "tags": [
                    "Colores"
                ],
                "summary": "Crear un nuevo color",
                "description": "Crea un nuevo color utilizando los datos proporcionados en la solicitud y lo devuelve como una respuesta JSON",
                "operationId": "createColor",
                "requestBody": {
                    "description": "Datos del nuevo color",
                    "required": true,
                    "content": {
                        "application/json": {
                            "schema": {
                                "properties": {
                                    "nombre": {
                                        "type": "string",
                                        "example": "Azul"
                                    }
                                },
                                "type": "object"
                            }
                        }
                    }
                },
                "responses": {
                    "201": {
                        "description": "Color creado con éxito",
                        "content": {
                            "application/json": {
                                "schema": {
                                    "properties": {
                                        "message": {
                                            "type": "string",
                                            "example": "Color creado con éxito"
                                        },
                                        "color": {
                                            "properties": {
                                                "id": {
                                                    "type": "integer",
                                                    "example": 2
                                                },
                                                "nombre": {
                                                    "type": "string",
                                                    "example": "Azul"
                                                },
                                                "created_at": {
                                                    "type": "string",
                                                    "format": "date-time"
                                                },
                                                "updated_at": {
                                                    "type": "string",
                                                    "format": "date-time"
                                                }
                                            },
                                            "type": "object"
                                        }
                                    },
                                    "type": "object"
                                }
                            }
                        }
                    },
                    "422": {
                        "description": "Error de validación",
                        "content": {
                            "application/json": {
                                "schema": {
                                    "properties": {
                                        "message": {
                                            "type": "string",
                                            "example": "Los datos proporcionados no son válidos"
                                        },
                                        "errors": {
                                            "properties": {
                                                "nombre": {
                                                    "type": "array",
                                                    "items": {
                                                        "type": "string"
                                                    }
                                                }
                                            },
                                            "type": "object"
                                        }
                                    },
                                    "type": "object"
                                }
                            }
                        }
                    }
                },
                "security": [
                    {
                        "bearerAuth": []
                    }
                ]
            }
        },
        "/api/v1/colores/{id}": {
            "put": {
                "tags": [
                    "Colores"
                ],
                "summary": "Actualizar un color existente",
                "description": "Actualiza un color existente utilizando los datos proporcionados en la solicitud y lo devuelve como una respuesta JSON",
                "operationId": "updateColor",
                "parameters": [
                    {
                        "name": "id",
                        "in": "path",
                        "description": "ID del color a actualizar",
                        "required": true,
                        "schema": {
                            "type": "string"
                        }
                    }
                ],
                "requestBody": {
                    "description": "Datos actualizados del color",
                    "required": true,
                    "content": {
                        "application/json": {
                            "schema": {
                                "properties": {
                                    "nombre": {
                                        "type": "string",
                                        "example": "Verde"
                                    }
                                },
                                "type": "object"
                            }
                        }
                    }
                },
                "responses": {
                    "200": {
                        "description": "Color actualizado con éxito",
                        "content": {
                            "application/json": {
                                "schema": {
                                    "properties": {
                                        "message": {
                                            "type": "string",
                                            "example": "Color actualizado con éxito"
                                        },
                                        "color": {
                                            "properties": {
                                                "id": {
                                                    "type": "integer",
                                                    "example": 2
                                                },
                                                "nombre": {
                                                    "type": "string",
                                                    "example": "Verde"
                                                },
                                                "created_at": {
                                                    "type": "string",
                                                    "format": "date-time"
                                                },
                                                "updated_at": {
                                                    "type": "string",
                                                    "format": "date-time"
                                                }
                                            },
                                            "type": "object"
                                        }
                                    },
                                    "type": "object"
                                }
                            }
                        }
                    },
                    "404": {
                        "description": "Color no encontrado",
                        "content": {
                            "application/json": {
                                "schema": {
                                    "properties": {
                                        "message": {
                                            "type": "string",
                                            "example": "Color no encontrado"
                                        }
                                    },
                                    "type": "object"
                                }
                            }
                        }
                    },
                    "422": {
                        "description": "Error de validación",
                        "content": {
                            "application/json": {
                                "schema": {
                                    "properties": {
                                        "message": {
                                            "type": "string",
                                            "example": "Los datos proporcionados no son válidos"
                                        },
                                        "errors": {
                                            "properties": {
                                                "nombre": {
                                                    "type": "array",
                                                    "items": {
                                                        "type": "string"
                                                    }
                                                }
                                            },
                                            "type": "object"
                                        }
                                    },
                                    "type": "object"
                                }
                            }
                        }
                    }
                },
                "security": [
                    {
                        "bearerAuth": []
                    }
                ]
            },
            "delete": {
                "tags": [
                    "Colores"
                ],
                "summary": "Eliminar un color existente",
                "description": "Elimina un color existente por su ID y lo devuelve como una respuesta JSON",
                "operationId": "deleteColor",
                "parameters": [
                    {
                        "name": "id",
                        "in": "path",
                        "description": "ID del color a eliminar",
                        "required": true,
                        "schema": {
                            "type": "string"
                        }
                    }
                ],
                "responses": {
                    "200": {
                        "description": "Color eliminado con éxito",
                        "content": {
                            "application/json": {
                                "schema": {
                                    "properties": {
                                        "message": {
                                            "type": "string",
                                            "example": "Color eliminado con éxito"
                                        }
                                    },
                                    "type": "object"
                                }
                            }
                        }
                    },
                    "404": {
                        "description": "Color no encontrado",
                        "content": {
                            "application/json": {
                                "schema": {
                                    "properties": {
                                        "message": {
                                            "type": "string",
                                            "example": "Color no encontrado"
                                        }
                                    },
                                    "type": "object"
                                }
                            }
                        }
                    },
                    "400": {
                        "description": "No se pudo borrar el color, tiene cervezas relacionadas",
                        "content": {
                            "application/json": {
                                "schema": {
                                    "properties": {
                                        "message": {
                                            "type": "string",
                                            "example": "No se pudo borrar el color, tiene cervezas relacionadas"
                                        }
                                    },
                                    "type": "object"
                                }
                            }
                        }
                    }
                },
                "security": [
                    {
                        "bearerAuth": []
                    }
                ]
            }
        },
        "/api/register": {
            "post": {
                "tags": [
                    "Authentication"
                ],
                "summary": "Register a new user",
                "description": "Registers a new user and returns an authorization token",
                "operationId": "register",
                "requestBody": {
                    "required": true,
                    "content": {
                        "application/json": {
                            "schema": {
                                "properties": {
                                    "name": {
                                        "type": "string",
                                        "example": "John Doe"
                                    },
                                    "email": {
                                        "type": "string",
                                        "example": "newuser@example.com"
                                    },
                                    "password": {
                                        "type": "string",
                                        "example": "newpassword"
                                    }
                                },
                                "type": "object"
                            }
                        }
                    }
                },
                "responses": {
                    "200": {
                        "description": "Successful registration",
                        "content": {
                            "application/json": {
                                "schema": {
                                    "properties": {
                                        "status": {
                                            "type": "string"
                                        },
                                        "message": {
                                            "type": "string"
                                        },
                                        "user": {
                                            "type": "object"
                                        },
                                        "authorization": {
                                            "properties": {
                                                "token": {
                                                    "type": "string"
                                                },
                                                "type": {
                                                    "type": "string",
                                                    "example": "bearer"
                                                }
                                            },
                                            "type": "object"
                                        }
                                    },
                                    "type": "object"
                                }
                            }
                        }
                    },
                    "422": {
                        "description": "Validation error",
                        "content": {
                            "application/json": {
                                "schema": {
                                    "properties": {
                                        "errors": {
                                            "type": "object"
                                        }
                                    },
                                    "type": "object"
                                }
                            }
                        }
                    }
                }
            }
        },
        "/api/login": {
            "post": {
                "tags": [
                    "Authentication"
                ],
                "summary": "Login an existing user",
                "description": "Logs in an existing user and returns an authorization token",
                "operationId": "login",
                "requestBody": {
                    "required": true,
                    "content": {
                        "application/json": {
                            "schema": {
                                "properties": {
                                    "email": {
                                        "type": "string",
                                        "example": "user@example.com"
                                    },
                                    "password": {
                                        "type": "string",
                                        "example": "password"
                                    }
                                },
                                "type": "object"
                            }
                        }
                    }
                },
                "responses": {
                    "200": {
                        "description": "Successful login",
                        "content": {
                            "application/json": {
                                "schema": {
                                    "properties": {
                                        "user": {
                                            "type": "object"
                                        },
                                        "authorization": {
                                            "properties": {
                                                "token": {
                                                    "type": "string"
                                                },
                                                "type": {
                                                    "type": "string",
                                                    "example": "bearer"
                                                }
                                            },
                                            "type": "object"
                                        }
                                    },
                                    "type": "object"
                                }
                            }
                        }
                    },
                    "401": {
                        "description": "Unauthorized",
                        "content": {
                            "application/json": {
                                "schema": {
                                    "properties": {
                                        "message": {
                                            "type": "string"
                                        }
                                    },
                                    "type": "object"
                                }
                            }
                        }
                    },
                    "422": {
                        "description": "Validation error",
                        "content": {
                            "application/json": {
                                "schema": {
                                    "properties": {
                                        "errors": {
                                            "type": "object"
                                        }
                                    },
                                    "type": "object"
                                }
                            }
                        }
                    }
                }
            }
        },
        "/api/v1/logout": {
            "post": {
                "tags": [
                    "Authentication"
                ],
                "summary": "Logout the authenticated user",
                "description": "Logs out the authenticated user",
                "operationId": "logout",
                "responses": {
                    "200": {
                        "description": "Successfully logged out",
                        "content": {
                            "application/json": {
                                "schema": {
                                    "properties": {
                                        "message": {
                                            "type": "string"
                                        }
                                    },
                                    "type": "object"
                                }
                            }
                        }
                    }
                },
                "security": [
                    {
                        "bearerAuth": []
                    }
                ]
            }
        },
        "/api/v1/refresh": {
            "post": {
                "tags": [
                    "Authentication"
                ],
                "summary": "Refresh the authentication token",
                "description": "Refreshes the authentication token for the authenticated user",
                "operationId": "refresh",
                "responses": {
                    "200": {
                        "description": "Successfully refreshed token",
                        "content": {
                            "application/json": {
                                "schema": {
                                    "properties": {
                                        "user": {
                                            "type": "object"
                                        },
                                        "authorization": {
                                            "properties": {
                                                "token": {
                                                    "type": "string"
                                                },
                                                "type": {
                                                    "type": "string",
                                                    "example": "bearer"
                                                }
                                            },
                                            "type": "object"
                                        }
                                    },
                                    "type": "object"
                                }
                            }
                        }
                    }
                },
                "security": [
                    {
                        "bearerAuth": []
                    }
                ]
            }
        }
    },
    "components": {
        "schemas": {
            "Cerveza": {
                "properties": {
                    "id": {
                        "type": "integer"
                    },
                    "nombre": {
                        "type": "string"
                    },
                    "descripcion": {
                        "type": "string"
                    },
                    "color": {
                        "type": "string"
                    },
                    "graduacion": {
                        "type": "string"
                    },
                    "tipo": {
                        "type": "string"
                    },
                    "pais": {
                        "type": "string"
                    },
                    "novedad": {
                        "type": "boolean"
                    },
                    "oferta": {
                        "type": "boolean"
                    },
                    "precio": {
                        "type": "number"
                    },
                    "foto": {
                        "type": "string"
                    },
                    "marca": {
                        "type": "string"
                    }
                },
                "type": "object"
            }
        },
        "securitySchemes": {
            "bearerAuth": {
                "type": "http",
                "description": "Autenticación Bearer JWT",
                "scheme": "bearer"
            }
        }
    }
}